directus_api.py
directus_python_client-1.0.5.dist-info/METADATA
directus_python_client-1.0.5.dist-info/WHEEL
directus_python_client-1.0.5.dist-info/entry_points.txt
directus_python_client-1.0.5.dist-info/top_level.txt
directus_python_client-1.0.5.dist-info/RECORD
