Metadata-Version: 2.1
Name: directus-python-client
Version: 1.0.5
Summary: A bunch of scripts that abstracts the Directus-REST-Api for faster development.
Author-email: Quving <vinh-ngu@hotmail.com>
Project-URL: Homepage, https://github.com/Quving/directus-python-client
Keywords: python,directus
Classifier: License :: OSI Approved :: MIT License
Classifier: Programming Language :: Python
Classifier: Programming Language :: Python :: 3
Requires-Python: >=3.6
Requires-Dist: requests (==2.28.1)
